kosmosx/__init__.py
kosmosx/model.py
kosmosx/train.py
kosmosx-0.3.1.dist-info/LICENSE
kosmosx-0.3.1.dist-info/WHEEL
kosmosx-0.3.1.dist-info/METADATA
kosmosx-0.3.1.dist-info/RECORD
