Metadata-Version: 2.1
Name: kosmosx
Version: 0.3.1
Summary: Transformers at zeta scales
Home-page: https://github.com/kyegomez/Kosmos-X
License: MIT
Keywords: Transformers,zeta scale
Author: Zeta Team
Author-email: kye@apac.ai
Requires-Python: >=3.8,<4.0
Classifier: License :: OSI Approved :: MIT License
Classifier: Programming Language :: Python :: 3
Classifier: Programming Language :: Python :: 3.8
Classifier: Programming Language :: Python :: 3.9
Classifier: Programming Language :: Python :: 3.10
Classifier: Programming Language :: Python :: 3.11
Classifier: Programming Language :: Python :: 3
Requires-Dist: accelerate (==0.22.0)
Requires-Dist: beartype (==0.15.0)
Requires-Dist: bitsandbytes (==0.38.1)
Requires-Dist: colt5-attention (==0.10.19)
Requires-Dist: datasets (==2.10.1)
Requires-Dist: einops (==0.7.0)
Requires-Dist: einops-exts (==0.0.4)
Requires-Dist: fairscale (==0.4.0)
Requires-Dist: lion-pytorch (==0.0.7)
Requires-Dist: pytest (==7.4.2)
Requires-Dist: rich (==13.5.2)
Requires-Dist: scipy (==1.9.3)
Requires-Dist: sentencepiece (==0.1.98)
Requires-Dist: tiktoken (==0.4.0)
Requires-Dist: timm (==0.6.13)
Requires-Dist: tokenmonster (==1.1.12)
Requires-Dist: torch (==2.1.1)
Requires-Dist: torchdiffeq (==0.2.3)
Requires-Dist: torchvision (==0.16.1)
Requires-Dist: tqdm (==4.66.1)
Requires-Dist: transformers (==4.35.0)
Requires-Dist: typing (==3.7.4.3)
Requires-Dist: vector-quantize-pytorch (==1.12.0)
Requires-Dist: zetascale
